{
 "signatures": [
  {
   "keyid": "d7d2d47a3f644fc3a685bac7b39c81ed9f9cee48ff861b44fbd86b91e34e7829",
   "sig": ""
  }
 ],
 "signed": {
  "_type": "targets",
  "delegations": {
   "keys": {},
   "roles": [
    {
     "keyids": [],
     "name": "new-delegate",
     "paths": [
      "new-delegate/*",
      "new-delegate/*/*",
      "new-delegate/*/*/*",
      "new-delegate/*/*/*/*"
     ],
     "terminating": true,
     "threshold": 1
    }
   ]
  },
  "expires": "2025-08-07T13:06:05Z",
  "spec_version": "1.0.31",
  "targets": {
   "bar": {
    "hashes": {
     "sha256": "b5bb9d8014a0f9b1d61e21e796d78dccdf1352f23cd32812f4850b878ae4944c"
    },
    "length": 4
   },
   "new": {
    "hashes": {
     "sha256": "7aa7a5359173d05b63cfd682e3c38487f3cb4f7f1d60659fe59fab1505977d4c"
    },
    "length": 4
   }
  },
  "version": 16,
  "x-tuf-on-ci-expiry-period": 360,
  "x-tuf-on-ci-signing-period": 60
 }
}